pypresentation/__init__.py
pypresentation/__main__.py
pypresentation/presentation.py
pypresentation/slide.py
pypresentation/templates.py
pypresentation-0.1.1.dist-info/LICENSE
pypresentation-0.1.1.dist-info/METADATA
pypresentation-0.1.1.dist-info/WHEEL
pypresentation-0.1.1.dist-info/RECORD
