Metadata-Version: 2.1
Name: pypresentation
Version: 0.1.1
Summary: 
License: MIT
Author: Petr Rudichev
Author-email: petrrudichev@gmail.com
Requires-Python: >=3.12,<4.0
Classifier: License :: OSI Approved :: MIT License
Classifier: Programming Language :: Python :: 3
Classifier: Programming Language :: Python :: 3.12
Requires-Dist: keyboard (>=0.13.5,<0.14.0)
Requires-Dist: rich (>=13.8.0,<14.0.0)
Requires-Dist: rich-pixels (>=3.0.1,<4.0.0)
